{"v":"5.9.0","fr":25,"ip":0,"op":100,"w":1920,"h":1080,"nm":"Comp 1","ddd":0,"assets":[],"layers":[{"ddd":0,"ind":1,"ty":4,"nm":"Shape Layer 2","sr":1,"ks":{"o":{"a":0,"k":100,"ix":11},"r":{"a":0,"k":-180,"ix":10},"p":{"a":0,"k":[958,538,0],"ix":2,"l":2},"a":{"a":0,"k":[-126,10,0],"ix":1,"l":2},"s":{"a":0,"k":[94.067,86.467,100],"ix":6,"l":2}},"ao":0,"shapes":[{"ty":"gr","it":[{"ty":"rc","d":1,"s":{"a":0,"k":[2000,1200],"ix":2},"p":{"a":0,"k":[0,0],"ix":3},"r":{"a":0,"k":40,"ix":4},"nm":"Rectangle Path 1","mn":"ADBE Vector Shape - Rect","hd":false},{"ty":"gs","o":{"a":0,"k":100,"ix":9},"w":{"a":0,"k":24,"ix":10},"g":{"p":3,"k":{"a":0,"k":[0,1,1,1,0.5,1,1,1,1,1,1,1],"ix":8}},"s":{"a":1,"k":[{"i":{"x":0.833,"y":0.833},"o":{"x":0.167,"y":0.167},"t":0,"s":[999.291,-606.014],"to":[0,101.773],"ti":[0.709,-200.463]},{"i":{"x":0.833,"y":0.833},"o":{"x":0.167,"y":0.167},"t":15,"s":[999.291,4.626],"to":[-0.709,200.463],"ti":[167.257,-97.918]},{"i":{"x":0.833,"y":0.833},"o":{"x":0.167,"y":0.167},"t":25,"s":[995.039,596.762],"to":[-167.257,97.918],"ti":[332.388,0]},{"i":{"x":0.833,"y":0.833},"o":{"x":0.167,"y":0.167},"t":40,"s":[-4.252,592.136],"to":[-332.388,0],"ti":[167.257,99.46]},{"i":{"x":0.833,"y":0.833},"o":{"x":0.167,"y":0.167},"t":50,"s":[-999.291,596.762],"to":[-167.257,-99.46],"ti":[-0.709,198.921]},{"i":{"x":0.833,"y":0.833},"o":{"x":0.167,"y":0.167},"t":65,"s":[-1007.796,-4.626],"to":[0.709,-198.921],"ti":[-167.966,101.002]},{"i":{"x":0.833,"y":0.833},"o":{"x":0.167,"y":0.167},"t":75,"s":[-995.039,-596.762],"to":[167.966,-101.002],"ti":[-315.379,2.313]},{"i":{"x":0.833,"y":0.833},"o":{"x":0.167,"y":0.167},"t":90,"s":[0,-610.64],"to":[315.379,-2.313],"ti":[-149.539,0]},{"t":100,"s":[897.236,-610.64]}],"ix":4},"e":{"a":1,"k":[{"i":{"x":0.833,"y":0.833},"o":{"x":0.167,"y":0.167},"t":0,"s":[1006.488,0],"to":[-1.417,98.689],"ti":[166.549,-99.46]},{"i":{"x":0.833,"y":0.833},"o":{"x":0.167,"y":0.167},"t":15,"s":[997.984,592.136],"to":[-166.549,99.46],"ti":[333.097,0]},{"i":{"x":0.833,"y":0.833},"o":{"x":0.167,"y":0.167},"t":25,"s":[7.197,596.762],"to":[-333.097,0],"ti":[168.675,101.773]},{"i":{"x":0.833,"y":0.833},"o":{"x":0.167,"y":0.167},"t":40,"s":[-1000.599,592.136],"to":[-168.675,-101.773],"ti":[0,198.921]},{"i":{"x":0.833,"y":0.833},"o":{"x":0.167,"y":0.167},"t":50,"s":[-1004.851,-13.878],"to":[0,-198.921],"ti":[-166.549,99.46]},{"i":{"x":0.833,"y":0.833},"o":{"x":0.167,"y":0.167},"t":65,"s":[-1000.599,-601.388],"to":[166.549,-99.46],"ti":[-334.515,0]},{"i":{"x":0.833,"y":0.833},"o":{"x":0.167,"y":0.167},"t":75,"s":[-5.56,-610.64],"to":[334.515,0],"ti":[-168.675,-1.542]},{"t":90,"s":[1006.488,-601.388]}],"ix":5},"t":1,"lc":1,"lj":1,"ml":4,"ml2":{"a":0,"k":4,"ix":13},"bm":0,"nm":"Gradient Stroke 1","mn":"ADBE Vector Graphic - G-Stroke","hd":false},{"ty":"tr","p":{"a":0,"k":[-126,10],"ix":2},"a":{"a":0,"k":[0,0],"ix":1},"s":{"a":0,"k":[100,100],"ix":3},"r":{"a":0,"k":0,"ix":6},"o":{"a":0,"k":100,"ix":7},"sk":{"a":0,"k":0,"ix":4},"sa":{"a":0,"k":0,"ix":5},"nm":"Transform"}],"nm":"Rectangle 1","np":3,"cix":2,"bm":0,"ix":1,"mn":"ADBE Vector Group","hd":false},{"ty":"tm","s":{"a":1,"k":[{"i":{"x":[0.833],"y":[0.833]},"o":{"x":[0.167],"y":[0.167]},"t":0,"s":[0]},{"i":{"x":[0.833],"y":[0.833]},"o":{"x":[0.167],"y":[0.167]},"t":15,"s":[9]},{"i":{"x":[0.833],"y":[0.833]},"o":{"x":[0.167],"y":[0.167]},"t":25,"s":[18]},{"i":{"x":[0.833],"y":[0.833]},"o":{"x":[0.167],"y":[0.167]},"t":40,"s":[34]},{"i":{"x":[0.833],"y":[0.833]},"o":{"x":[0.167],"y":[0.167]},"t":50,"s":[48]},{"i":{"x":[0.833],"y":[0.833]},"o":{"x":[0.167],"y":[0.167]},"t":65,"s":[58]},{"i":{"x":[0.833],"y":[0.833]},"o":{"x":[0.167],"y":[0.167]},"t":75,"s":[68]},{"i":{"x":[0.833],"y":[0.833]},"o":{"x":[0.167],"y":[0.167]},"t":90,"s":[84]},{"t":100,"s":[98]}],"ix":1},"e":{"a":1,"k":[{"i":{"x":[0.833],"y":[0.833]},"o":{"x":[0.167],"y":[0.167]},"t":0,"s":[9]},{"i":{"x":[0.833],"y":[0.833]},"o":{"x":[0.167],"y":[0.167]},"t":15,"s":[19]},{"i":{"x":[0.833],"y":[0.833]},"o":{"x":[0.167],"y":[0.167]},"t":25,"s":[34]},{"i":{"x":[0.833],"y":[0.833]},"o":{"x":[0.167],"y":[0.167]},"t":40,"s":[50]},{"i":{"x":[0.833],"y":[0.833]},"o":{"x":[0.167],"y":[0.167]},"t":50,"s":[59]},{"i":{"x":[0.833],"y":[0.833]},"o":{"x":[0.167],"y":[0.167]},"t":65,"s":[69]},{"i":{"x":[0.833],"y":[0.833]},"o":{"x":[0.167],"y":[0.167]},"t":75,"s":[84]},{"i":{"x":[0.833],"y":[0.833]},"o":{"x":[0.167],"y":[0.167]},"t":90,"s":[96]},{"t":100,"s":[100]}],"ix":2},"o":{"a":0,"k":0,"ix":3},"m":1,"ix":2,"nm":"Trim Paths 1","mn":"ADBE Vector Filter - Trim","hd":false}],"ip":0,"op":125,"st":0,"bm":0},{"ddd":0,"ind":2,"ty":4,"nm":"Shape Layer 1","sr":1,"ks":{"o":{"a":0,"k":100,"ix":11},"r":{"a":0,"k":0,"ix":10},"p":{"a":0,"k":[950,558,0],"ix":2,"l":2},"a":{"a":0,"k":[-126,10,0],"ix":1,"l":2},"s":{"a":0,"k":[64.467,64.467,100],"ix":6,"l":2}},"ao":0,"shapes":[{"ty":"gr","it":[{"ty":"rc","d":1,"s":{"a":0,"k":[2000,1200],"ix":2},"p":{"a":0,"k":[0,0],"ix":3},"r":{"a":0,"k":40,"ix":4},"nm":"Rectangle Path 1","mn":"ADBE Vector Shape - Rect","hd":false},{"ty":"gs","o":{"a":0,"k":100,"ix":9},"w":{"a":0,"k":24,"ix":10},"g":{"p":3,"k":{"a":0,"k":[0,1,1,1,0.5,1,1,1,1,1,1,1],"ix":8}},"s":{"a":1,"k":[{"i":{"x":0.833,"y":0.833},"o":{"x":0.167,"y":0.167},"t":0,"s":[1001.431,4.652],"to":[0,100.795],"ti":[166.195,-100.02]},{"i":{"x":0.833,"y":0.833},"o":{"x":0.167,"y":0.167},"t":15,"s":[1001.431,609.423],"to":[-166.195,100.02],"ti":[333.1,-0.775]},{"i":{"x":0.833,"y":0.833},"o":{"x":0.167,"y":0.167},"t":25,"s":[4.261,604.771],"to":[-333.1,0.775],"ti":[167.615,100.795]},{"i":{"x":0.833,"y":0.833},"o":{"x":0.167,"y":0.167},"t":40,"s":[-997.17,614.075],"to":[-167.615,-100.795],"ti":[0.71,203.141]},{"i":{"x":0.833,"y":0.833},"o":{"x":0.167,"y":0.167},"t":50,"s":[-1001.431,0],"to":[-0.71,-203.141],"ti":[-167.615,98.469]},{"i":{"x":0.833,"y":0.833},"o":{"x":0.167,"y":0.167},"t":65,"s":[-1001.431,-604.771],"to":[167.615,-98.469],"ti":[-334.521,-2.326]},{"i":{"x":0.833,"y":0.833},"o":{"x":0.167,"y":0.167},"t":75,"s":[4.261,-590.815],"to":[334.521,2.326],"ti":[-166.905,0]},{"t":90,"s":[1005.693,-590.815]}],"ix":4},"e":{"a":1,"k":[{"i":{"x":0.833,"y":0.833},"o":{"x":0.167,"y":0.167},"t":0,"s":[1003.419,-595.467],"to":[-0.71,100.02],"ti":[0,-200.04]},{"i":{"x":0.833,"y":0.833},"o":{"x":0.167,"y":0.167},"t":15,"s":[999.157,4.652],"to":[0,200.04],"ti":[165.485,-100.02]},{"i":{"x":0.833,"y":0.833},"o":{"x":0.167,"y":0.167},"t":25,"s":[1003.419,604.771],"to":[-165.485,100.02],"ti":[334.521,1.551]},{"i":{"x":0.833,"y":0.833},"o":{"x":0.167,"y":0.167},"t":40,"s":[6.249,604.771],"to":[-334.521,-1.551],"ti":[167.615,101.571]},{"i":{"x":0.833,"y":0.833},"o":{"x":0.167,"y":0.167},"t":50,"s":[-1003.705,595.467],"to":[-167.615,-101.571],"ti":[0,198.489]},{"i":{"x":0.833,"y":0.833},"o":{"x":0.167,"y":0.167},"t":65,"s":[-999.444,-4.652],"to":[0,-198.489],"ti":[-166.905,96.918]},{"i":{"x":0.833,"y":0.833},"o":{"x":0.167,"y":0.167},"t":75,"s":[-1003.705,-595.467],"to":[166.905,-96.918],"ti":[-314.634,-0.775]},{"i":{"x":0.833,"y":0.833},"o":{"x":0.167,"y":0.167},"t":90,"s":[1.988,-586.163],"to":[314.634,0.775],"ti":[-147.019,0.775]},{"t":100,"s":[884.099,-590.815]}],"ix":5},"t":1,"lc":1,"lj":1,"ml":4,"ml2":{"a":0,"k":4,"ix":13},"bm":0,"nm":"Gradient Stroke 1","mn":"ADBE Vector Graphic - G-Stroke","hd":false},{"ty":"tr","p":{"a":0,"k":[-110,-26],"ix":2},"a":{"a":0,"k":[0,0],"ix":1},"s":{"a":0,"k":[145.603,133.376],"ix":3},"r":{"a":0,"k":0,"ix":6},"o":{"a":0,"k":100,"ix":7},"sk":{"a":0,"k":0,"ix":4},"sa":{"a":0,"k":0,"ix":5},"nm":"Transform"}],"nm":"Rectangle 1","np":3,"cix":2,"bm":0,"ix":1,"mn":"ADBE Vector Group","hd":false},{"ty":"tm","s":{"a":1,"k":[{"i":{"x":[0.833],"y":[0.833]},"o":{"x":[0.167],"y":[0.167]},"t":0,"s":[0]},{"i":{"x":[0.833],"y":[0.833]},"o":{"x":[0.167],"y":[0.167]},"t":15,"s":[9]},{"i":{"x":[0.833],"y":[0.833]},"o":{"x":[0.167],"y":[0.167]},"t":25,"s":[18]},{"i":{"x":[0.833],"y":[0.833]},"o":{"x":[0.167],"y":[0.167]},"t":40,"s":[34]},{"i":{"x":[0.833],"y":[0.833]},"o":{"x":[0.167],"y":[0.167]},"t":50,"s":[48]},{"i":{"x":[0.833],"y":[0.833]},"o":{"x":[0.167],"y":[0.167]},"t":65,"s":[58]},{"i":{"x":[0.833],"y":[0.833]},"o":{"x":[0.167],"y":[0.167]},"t":75,"s":[68]},{"i":{"x":[0.833],"y":[0.833]},"o":{"x":[0.167],"y":[0.167]},"t":90,"s":[84]},{"t":100,"s":[98]}],"ix":1},"e":{"a":1,"k":[{"i":{"x":[0.833],"y":[0.833]},"o":{"x":[0.167],"y":[0.167]},"t":0,"s":[9]},{"i":{"x":[0.833],"y":[0.833]},"o":{"x":[0.167],"y":[0.167]},"t":15,"s":[19]},{"i":{"x":[0.833],"y":[0.833]},"o":{"x":[0.167],"y":[0.167]},"t":25,"s":[34]},{"i":{"x":[0.833],"y":[0.833]},"o":{"x":[0.167],"y":[0.167]},"t":40,"s":[50]},{"i":{"x":[0.833],"y":[0.833]},"o":{"x":[0.167],"y":[0.167]},"t":50,"s":[59]},{"i":{"x":[0.833],"y":[0.833]},"o":{"x":[0.167],"y":[0.167]},"t":65,"s":[69]},{"i":{"x":[0.833],"y":[0.833]},"o":{"x":[0.167],"y":[0.167]},"t":75,"s":[84]},{"i":{"x":[0.833],"y":[0.833]},"o":{"x":[0.167],"y":[0.167]},"t":90,"s":[96]},{"t":100,"s":[100]}],"ix":2},"o":{"a":0,"k":0,"ix":3},"m":1,"ix":2,"nm":"Trim Paths 1","mn":"ADBE Vector Filter - Trim","hd":false}],"ip":0,"op":125,"st":0,"bm":0}],"markers":[]}